irlabpy/__init__.py
irlabpy/config.py
irlabpy/prod_config.ini
irlabpy/utils.py
irlabpy/cache/__init__.py
irlabpy/cache/cache.py
irlabpy/cache/tbase_client.py
irlabpy/data_model/__init__.py
irlabpy/data_model/feature.py
irlabpy/data_model/metrics.py
irlabpy/data_model/monitoring_item.py
irlabpy/data_model/serving.py
irlabpy/decorators/__init__.py
irlabpy/decorators/class_register.py
irlabpy/dev/__init__.py
irlabpy/dev/data_sync.py
irlabpy/dev/feature_data_service.py
irlabpy/dev/monitor_data_reader.py
irlabpy/dev/monitor_item_service.py
irlabpy/dev/request_util.py
irlabpy/feature_engineering/__init__.py
irlabpy/feature_engineering/base_feature_operator.py
irlabpy/feature_engineering/general_feature.py
irlabpy/irlabLogger/__init__.py
irlabpy/irlabLogger/irlab_logger.py
irlabpy/ops/__init__.py
irlabpy/pontus/__init__.py
irlabpy/pontus/event_tracking_proxy.py
irlabpy/pontus/pontus2_client.py
irlabpy/pontus/trend.py
irlabpy-0.3.3.dev2.dist-info/METADATA
irlabpy-0.3.3.dev2.dist-info/WHEEL
irlabpy-0.3.3.dev2.dist-info/top_level.txt
irlabpy-0.3.3.dev2.dist-info/RECORD
